multipartial/__init__.py
multipartial/api.py
multipartial/arguments.py
multipartial/array.py
multipartial/brackets.py
multipartial/partial.py
multipartial/require.py
multipartial-0.2.0.dist-info/WHEEL
multipartial-0.2.0.dist-info/METADATA
multipartial-0.2.0.dist-info/RECORD
