Metadata-Version: 2.3
Name: multipartial
Version: 0.2.0
Summary: N-dimensional arrays of partial functions.
Author-email: Kale Kundert <kale@thekunderts.net>
Requires-Python: ~=3.10
Classifier: Programming Language :: Python :: 3
Requires-Dist: reprfunc
Requires-Dist: sphinx ; extra == "doc"
Requires-Dist: sphinx_rtd_theme ; extra == "doc"
Requires-Dist: autoclasstoc ; extra == "doc"
Requires-Dist: pytest ; extra == "test"
Requires-Dist: parametrize_from_file ; extra == "test"
Project-URL: Bug Tracker, https://github.com/kalekundert/multipartial/issues
Project-URL: Continuous Integration, https://github.com/kalekundert/multipartial/actions
Project-URL: Documentation, https://multipartial.readthedocs.io/en/latest/
Project-URL: Test Coverage, https://app.codecov.io/github/kalekundert/multipartial
Project-URL: Version Control, https://github.com/kalekundert/multipartial
Provides-Extra: doc
Provides-Extra: test
